{"components_maz-bottom-sheet.md":"43dEGii9","components_maz-backdrop.md":"3xwyu5Fh","components_maz-accordion.md":"9MfSl9aE","components_maz-badge.md":"6HiU1Vty","components_maz-lazy-img.md":"AnMuOK9t","components_maz-carousel.md":"hRGKLoOE","components_maz-card.md":"AkeQa5Qi","components_maz-dialog.md":"MqE9Klw9","components_maz-dropdown.md":"wIvhw_YR","components_maz-checkbox.md":"M5BAqGFQ","components_maz-avatar.md":"dG67BxqT","components_maz-btn.md":"2LttdA2L","components_maz-gallery.md":"PzKOflzE","components_maz-chart.md":"TNjMoCnH","components_maz-dropzone.md":"BT5f8iGN","components_maz-phone-number-input.md":"OQuU2D4Z","components_maz-textarea.md":"dhd9vVOb","components_maz-transition-expand.md":"8HuhCPmm","composables_use-aos.md":"07Y5PT6V","guide_dark-mode.md":"qv-VwGMG","components_maz-tabs.md":"066bhcFB","directives_lazy-img.md":"c6AJ5J7s","directives_fullscreen-img.md":"woskBOzg","directives_click-outside.md":"yBmOUq35","components_maz-fullscreen-loader.md":"_X0114Di","components_maz-spinner.md":"yCi6twqf","plugins_aos.md":"wQLZoqfl","components_maz-input-number.md":"BYlbB9S5","components_maz-radio-buttons.md":"cFIIRgQh","helpers_date.md":"lLdzkotU","components_maz-stepper.md":"RzI6TRJI","components_maz-icon.md":"W4oiKTeu","index.md":"eOmhDWdO","components_maz-switch.md":"DIekpYzt","guide_nuxt.md":"D66S6D04","helpers_number.md":"RZX2evO8","guide_cli.md":"nJYaBxe7","composables_use-toast.md":"UrwkbF2b","composables_use-timer.md":"SE2AEmBJ","components_maz-input.md":"_URnOv5G","directives_zoom-img.md":"FxSef_J5","components_maz-select.md":"nplt3VKg","components_maz-picker.md":"Fse3BwMs","components_maz-slider.md":"F6bfMky1","components_maz-radio.md":"K0VPpnkd","components_maz-drawer.md":"bGR9N7YA","composables_use-theme-handler.md":"x2eRjcx3","plugins_wait.md":"FrD5EEEJ","plugins_toaster.md":"6YyM2Dy7","guide_colors.md":"qKA2BDtC","helpers_capitalize.md":"MAk6dDmZ","guide_theme.md":"iTe_rOn9","composables_use-idle-timeout.md":"_5d6TG71","components_maz-dialog-promise.md":"NcdAv-VN","components_maz-input-tags.md":"y_K9cfHG","components_maz-card-spotlight.md":"vCuZmRJP","helpers_country-code-to-unicode-flag.md":"BkX8dS5J","helpers_currency.md":"nXabAA03","composables_use-user-visibility.md":"8Os02IcA","components_maz-input-price.md":"KX9YmF8k","made-with-maz-ui.md":"pRO-tZ-d","composables_use-wait.md":"YDGp6SnG","guide_getting-started.md":"eBdp_yqn"}
