{"components_maz-bottom-sheet.md":"bb12ff0e","components_maz-avatar.md":"17184420","components_maz-radio-buttons.md":"84158697","components_maz-backdrop.md":"566d5495","components_maz-lazy-img.md":"e99c2d3c","components_maz-phone-number-input.md":"0dec1552","components_maz-badge.md":"1a9bc7c0","components_maz-transition-expand.md":"b80dc2e7","components_maz-slider.md":"7209630b","components_maz-select.md":"847ea37f","components_maz-chart.md":"f590e0b3","components_maz-checkbox.md":"ab1e76b0","components_maz-fullscreen-loader.md":"98c2668b","components_maz-input-price.md":"ab00d2ff","components_maz-input-number.md":"5b5dc1ad","components_maz-gallery.md":"8515e817","components_maz-input-tags.md":"e4b13571","components_maz-stepper.md":"3f1a052f","components_maz-input.md":"ebab611b","components_maz-picker.md":"e33e75c5","components_maz-icon.md":"3d4e381a","components_maz-dialog-promise.md":"bc7d923b","components_maz-dropzone.md":"5f2874f6","components_maz-switch.md":"7612b79f","components_maz-dialog.md":"f746da71","components_maz-spinner.md":"c51b5050","components_maz-tabs.md":"d1fd6f0e","components_maz-textarea.md":"9091f7d3","components_maz-carousel.md":"192daa9e","components_maz-card.md":"0ffddd99","components_maz-btn.md":"5a213492","components_maz-drawer.md":"6e462083","composables_use-aos.md":"59c3562f","composables_use-idle-timeout.md":"a42f5f06","composables_use-theme-handler.md":"9097e4ef","composables_use-user-visibility.md":"39ccc861","composables_use-toast.md":"144ecca7","directives_fullscreen-img.md":"e9908994","helpers_capitalize.md":"4ccf1a1f","helpers_number.md":"849c63c4","index.md":"53d3fc12","plugins_toaster.md":"9fd3b3c5","guide_theme.md":"2f74efd0","composables_use-wait.md":"5d8716b0","helpers_date.md":"504b51dd","directives_click-outside.md":"50172514","guide_colors.md":"854ebf46","guide_nuxt.md":"e4e76844","directives_lazy-img.md":"84d5df28","directives_zoom-img.md":"8f71f4c1","helpers_currency.md":"d5449b61","made-with-maz-ui.md":"a0afb6e5","plugins_wait.md":"ef555c83","plugins_aos.md":"cd5fb596","guide_dark-mode.md":"f2249066","guide_getting-started.md":"b35ac6e9"}
