{"components_maz-avatar.md":"b16ddec7","components_maz-backdrop.md":"20bb4644","components_maz-badge.md":"b0095c28","components_maz-bottom-sheet.md":"2d2c4d4c","components_maz-carousel.md":"911a06ac","components_maz-card.md":"edaf80cb","components_maz-btn.md":"f9944b03","components_maz-checkbox.md":"709334a3","components_maz-dialog-promise.md":"4bfef0de","components_maz-drawer.md":"e4f2851f","components_maz-picker.md":"d046cf5b","components_maz-input-number.md":"9c54909a","components_maz-gallery.md":"15463e03","components_maz-input.md":"d959d593","components_maz-dialog.md":"c05b6ae7","components_maz-lazy-img.md":"614559b0","components_maz-icon.md":"1e972c6b","components_maz-input-price.md":"85fcd651","components_maz-radio-buttons.md":"706b949d","components_maz-select.md":"9e764041","components_maz-slider.md":"ef12dbff","components_maz-spinner.md":"f2402bda","components_maz-input-tags.md":"c1dd8f2a","components_maz-stepper.md":"af6e6eea","components_maz-switch.md":"a8e7de5e","components_maz-tabs.md":"35983bda","composables_use-aos.md":"95ee8c81","components_maz-phone-number-input.md":"4b0b5ebb","helpers_currency.md":"d4215af9","components_maz-dropzone.md":"d36f5ecb","guide_colors.md":"a47f2c2d","guide_dark-mode.md":"206ed9ee","guide_getting-started.md":"17a7b8b2","helpers_capitalize.md":"d808f13b","helpers_date.md":"532c0b68","helpers_number.md":"f1bb6e4b","index.md":"d2ac92e0","plugins_aos.md":"9fb78743","plugins_toaster.md":"578f67f1","plugins_wait.md":"70121197","composables_use-theme-handler.md":"0ad77195","made-with-maz-ui.md":"a7561310","composables_use-toast.md":"61f69c71","composables_use-user-visibility.md":"89c015ae","directives_lazy-img.md":"b8395749","composables_use-wait.md":"2b419222","components_maz-textarea.md":"96a3d633","directives_click-outside.md":"3cc59ca9","components_maz-transition-expand.md":"f741e56e","directives_zoom-img.md":"5ad790d7","guide_theme.md":"f9913efb","composables_use-idle-timeout.md":"519f441c","components_maz-chart.md":"11612af9"}
