{"components_maz-accordion.md":"gZIjGfjn","components_maz-fullscreen-loader.md":"NTAZK-FU","components_maz-gallery.md":"phMCI_Td","components_maz-input-tags.md":"d_7ookcD","components_maz-card-spotlight.md":"v7jLvxfh","components_maz-backdrop.md":"Ig_3gU-r","components_maz-icon.md":"hbwk6Ll-","components_maz-avatar.md":"VXN-Ar9R","components_maz-stepper.md":"qTVWTvWh","components_maz-input-price.md":"UjOvlHv5","components_maz-dropzone.md":"oOXnPoM1","composables_use-wait.md":"CbcY6Nja","components_maz-dialog.md":"KlNLHwvc","components_maz-dropdown.md":"_mBjg-GJ","composables_use-toast.md":"jufv4T0N","composables_use-user-visibility.md":"NoED9EWP","components_maz-dialog-promise.md":"wCiBCx_p","components_maz-radio.md":"Ll4Ssqtl","components_maz-drawer.md":"olfogtGy","components_maz-lazy-img.md":"iLSjzAtF","components_maz-radio-buttons.md":"ud5HQy_B","components_maz-input.md":"NmvsZdVe","components_maz-chart.md":"nZkw_i3I","components_maz-checkbox.md":"tRRfltoN","components_maz-carousel.md":"LckABLen","components_maz-badge.md":"KeP-iJ8E","components_maz-phone-number-input.md":"n4PGMI_9","components_maz-card.md":"zXcdDJAH","components_maz-btn.md":"lydjaMgg","components_maz-spinner.md":"WI5U_ErE","components_maz-bottom-sheet.md":"i6DUWtNM","components_maz-select.md":"1sVLmjST","directives_fullscreen-img.md":"Bbczcojp","directives_lazy-img.md":"8fldAVmW","directives_zoom-img.md":"ZPbEE2kh","guide_cli.md":"nvzwZF-f","guide_colors.md":"ZUzNFtFQ","composables_use-theme-handler.md":"N-aiOlX6","composables_use-timer.md":"rPqqy3XX","directives_click-outside.md":"rKkXtMcg","guide_dark-mode.md":"bl2rxNy_","components_maz-switch.md":"HbQFF-hx","components_maz-tabs.md":"xCDjlWCG","components_maz-textarea.md":"HEjT91jB","helpers_capitalize.md":"4TgdHR5o","components_maz-transition-expand.md":"NzrRyJKK","composables_use-aos.md":"5j5uG7Ur","guide_getting-started.md":"fYx_p_uf","helpers_country-code-to-unicode-flag.md":"BteTDv_y","composables_use-idle-timeout.md":"JebXKNxe","components_maz-picker.md":"kwwLa8jQ","helpers_currency.md":"2vGjyxIi","helpers_date.md":"HJ4VLWu3","guide_theme.md":"WE1pBKWP","helpers_number.md":"UZQ-xQyB","made-with-maz-ui.md":"nVOdj4I0","plugins_aos.md":"RApn2pLN","index.md":"Y39bsYH_","guide_nuxt.md":"GAa-TB11","plugins_toaster.md":"MIApn1nD","plugins_wait.md":"jI8nMZMK","components_maz-input-number.md":"rmT1izbo","components_maz-slider.md":"qFWCLaOU"}
