{"components_maz-badge.md":"64e63c3c","components_maz-radio-buttons.md":"3e8d358f","components_maz-avatar.md":"e41e9a66","components_maz-backdrop.md":"22305b66","components_maz-bottom-sheet.md":"fe5b1d3b","components_maz-dropdown.md":"3207643c","components_maz-btn.md":"861ec903","components_maz-carousel.md":"8c9c7d74","components_maz-dialog.md":"1cf31030","components_maz-fullscreen-loader.md":"78ab53dd","components_maz-dropzone.md":"06727c2f","components_maz-dialog-promise.md":"d21d7907","components_maz-input-number.md":"0ffb6806","components_maz-drawer.md":"20e7fb4b","components_maz-picker.md":"6220e8fd","components_maz-lazy-img.md":"820a2b40","components_maz-checkbox.md":"f11f062a","components_maz-input-price.md":"02794032","components_maz-input.md":"34bcd4d1","components_maz-phone-number-input.md":"d917f54b","components_maz-gallery.md":"003183cd","plugins_toaster.md":"bdb27b23","plugins_wait.md":"ce24b2fd","components_maz-icon.md":"b247eec4","components_maz-chart.md":"3d6ae30a","components_maz-select.md":"9d7465bc","components_maz-stepper.md":"27bd9502","components_maz-switch.md":"2fa8b1f0","components_maz-tabs.md":"2b8f080a","directives_fullscreen-img.md":"32f6d330","directives_lazy-img.md":"3c7c907f","components_maz-textarea.md":"07ff4d16","components_maz-input-tags.md":"84d8177c","components_maz-transition-expand.md":"d77ba09d","composables_use-aos.md":"2e5dc796","composables_use-theme-handler.md":"8eb0196d","composables_use-toast.md":"353571df","composables_use-wait.md":"b7546e7a","directives_zoom-img.md":"06b3b5dd","components_maz-card.md":"ef3706fc","guide_cli.md":"dd3d0b30","components_maz-spinner.md":"f59d200d","guide_colors.md":"74a2e820","guide_dark-mode.md":"4c3c89d7","guide_getting-started.md":"53539c2b","directives_click-outside.md":"0694f32f","guide_nuxt.md":"ea944c24","guide_theme.md":"42c8b191","helpers_capitalize.md":"7bf7ff65","components_maz-slider.md":"39b35240","helpers_number.md":"a6f9d8cf","made-with-maz-ui.md":"600c61d1","plugins_aos.md":"492a5fcd","index.md":"030e3fd7","helpers_currency.md":"bca37eac","helpers_date.md":"df9c441b","composables_use-idle-timeout.md":"c233595c","composables_use-user-visibility.md":"4c6e5dcc"}
