{"components_maz-spinner.md":"bc212388","components_maz-slider.md":"7134229e","components_maz-tabs.md":"2eac9477","components_maz-stepper.md":"ee65d691","components_maz-textarea.md":"c38edd30","components_maz-transition-expand.md":"f1ceac01","composables_use-aos.md":"da388431","composables_use-idle-timeout.md":"4447ad27","composables_use-user-visibility.md":"c1b81240","composables_use-toast.md":"c2de74ff","composables_use-theme-handler.md":"de141421","composables_use-wait.md":"5c612cb2","directives_click-outside.md":"fc169a59","guide_nuxt.md":"4023efb2","guide_theme.md":"66bcfcae","helpers_capitalize.md":"7d34ce88","helpers_currency.md":"71d0bb81","helpers_date.md":"91eed242","helpers_number.md":"a0e013a5","index.md":"84dcb7ac","made-with-maz-ui.md":"8ce67517","plugins_aos.md":"2c384c38","plugins_toaster.md":"fd1c97ed","components_maz-btn.md":"2aab8be2","components_maz-avatar.md":"76abcb9a","helpers_country-code-to-unicode-flag.md":"45b9938b","components_maz-switch.md":"eaadd6d8","components_maz-backdrop.md":"02487f3a","components_maz-badge.md":"fe1a7284","components_maz-bottom-sheet.md":"2859c00e","components_maz-dropzone.md":"1fb6b7f8","directives_fullscreen-img.md":"21e74998","components_maz-phone-number-input.md":"39249935","components_maz-chart.md":"eb85312c","components_maz-carousel.md":"52ca6053","directives_zoom-img.md":"7c966d4f","components_maz-drawer.md":"802b0b1d","components_maz-dialog.md":"21662e60","components_maz-dialog-promise.md":"4a8ed917","components_maz-icon.md":"282dc0c2","components_maz-picker.md":"a53636c7","components_maz-radio-buttons.md":"9434e605","components_maz-select.md":"209df854","components_maz-radio.md":"0085f483","components_maz-fullscreen-loader.md":"016ed566","components_maz-dropdown.md":"68892b56","components_maz-input-price.md":"e23c38a5","components_maz-input-number.md":"f75b08a4","components_maz-input.md":"57715262","components_maz-lazy-img.md":"db22e4cd","directives_lazy-img.md":"a9c7d788","guide_cli.md":"024bbe57","guide_getting-started.md":"c81a4aeb","components_maz-gallery.md":"a50f7bf5","components_maz-input-tags.md":"0aac247d","plugins_wait.md":"3d402997","components_maz-card.md":"81627f96","guide_colors.md":"afe46c7f","guide_dark-mode.md":"68fee4fa","components_maz-checkbox.md":"0b362427"}
